README.md
setup.py
BiostarHandbook.egg-info/PKG-INFO
BiostarHandbook.egg-info/SOURCES.txt
BiostarHandbook.egg-info/dependency_links.txt
BiostarHandbook.egg-info/entry_points.txt
BiostarHandbook.egg-info/requires.txt
BiostarHandbook.egg-info/top_level.txt
handbook/__init__.py
handbook/__main__.py
handbook/bio.py
handbook/combine.py
handbook/common.py
handbook/file_filter.py
handbook/genbank.py
handbook/genotype.py
handbook/metadata.py
handbook/mutate.py
handbook/mydecs.py
handbook/taxa.py
handbook/taxonomy.py
handbook/test.py
handbook/utils.py
handbook/version.py