Metadata-Version: 2.1
Name: BiostarHandbook
Version: 0.0.6
Summary: Utilities for the Biostar Handbook 
Home-page: https://github.com/biostars/biostar-handbook-code
Author: Istvan Albert
Author-email: istvan.albert@gmail.com
License: UNKNOWN
Platform: UNKNOWN
Classifier: Programming Language :: Python :: 3
Classifier: License :: OSI Approved :: MIT License
Classifier: Operating System :: OS Independent
Requires-Python: >=3.6
